{
  "jsonSchema": {
    "$schema": "http://json-schema.org/draft-07/schema#",
    "type": "object",
    "title": "Cato Networks collector configuration.",
    "properties": {
      "update_every": {
        "title": "Update every",
        "description": "Data collection interval, in seconds.",
        "type": "integer",
        "minimum": 60,
        "default": 60
      },
      "autodetection_retry": {
        "title": "Detection retry",
        "description": "Recheck interval in seconds. Zero disables retries.",
        "type": "integer",
        "minimum": 0,
        "default": 0
      },
      "url": {
        "title": "Cato API URL",
        "description": "Cato GraphQL API endpoint. Production endpoints must use HTTPS; HTTP is accepted only for loopback test endpoints.",
        "type": "string",
        "format": "uri",
        "default": "https://api.catonetworks.com/api/v1/graphql2"
      },
      "account_id": {
        "title": "Account ID",
        "description": "Cato account ID.",
        "type": "string",
        "minLength": 1
      },
      "api_key": {
        "title": "API key",
        "description": "Cato API key.",
        "type": "string",
        "minLength": 1
      },
      "site_selector": {
        "title": "Site selector",
        "description": "Space-separated simple patterns matched against Cato site ID or site name. Use exclusions such as '!lab-* *'. Exclusions win across site identity fields.",
        "type": "string",
        "default": "*"
      },
      "interface_selector": {
        "title": "Interface selector",
        "description": "Space-separated simple patterns matched against Cato interface ID or interface name. Use exclusions such as '!test-* *'. Exclusions win across interface identity fields.",
        "type": "string",
        "default": "*"
      },
      "limits": {
        "title": "Cardinality limits",
        "type": "object",
        "properties": {
          "max_sites": {
            "title": "Maximum selected sites",
            "description": "Maximum Cato sites collected after site_selector filtering. Set to 0 to disable this cap.",
            "type": "integer",
            "minimum": 0,
            "maximum": 100000,
            "default": 500
          },
          "max_interfaces_per_site": {
            "title": "Maximum interfaces per site",
            "description": "Maximum interfaces collected per selected site after interface_selector filtering. Set to 0 to disable this cap.",
            "type": "integer",
            "minimum": 0,
            "maximum": 10000,
            "default": 32
          }
        }
      },
      "timeout": {
        "title": "Timeout",
        "description": "HTTP request timeout.",
        "type": "number",
        "minimum": 0,
        "default": 30
      },
      "proxy_url": {
        "title": "Proxy URL",
        "description": "HTTP proxy URL. Empty value uses environment proxy variables.",
        "type": "string"
      },
      "discovery": {
        "title": "Discovery",
        "type": "object",
        "properties": {
          "refresh_every": {
            "title": "Discovery refresh interval",
            "description": "Site discovery refresh interval, in seconds.",
            "type": "integer",
            "minimum": 60,
            "default": 300
          },
          "page_limit": {
            "title": "Discovery page size",
            "description": "Maximum sites requested per entityLookup page.",
            "type": "integer",
            "minimum": 1,
            "maximum": 1000,
            "default": 100
          }
        }
      },
      "metrics": {
        "title": "Metrics",
        "type": "object",
        "properties": {
          "enabled": {
            "title": "Collect account metrics",
            "description": "Controls accountMetrics collection.",
            "type": "string",
            "enum": [
              "auto",
              "enabled",
              "disabled"
            ],
            "default": "auto"
          },
          "time_frame": {
            "title": "Metrics timeframe",
            "description": "Cato TimeFrame string used for accountMetrics, for example last.PT5M or utc.2020-02-11/{04:50:15--16:50:15}.",
            "type": "string",
            "pattern": "^(last\\.P[A-Z0-9]+|utc\\.\\S+)$",
            "default": "last.PT5M"
          },
          "buckets": {
            "title": "Metrics buckets",
            "description": "Number of accountMetrics buckets requested.",
            "type": "integer",
            "minimum": 1,
            "maximum": 1000,
            "default": 5
          },
          "group_interfaces": {
            "title": "Group by interfaces",
            "description": "Controls the accountMetrics groupInterfaces argument. auto leaves the argument unset so Cato applies its default; enabled and disabled send explicit true or false.",
            "type": "string",
            "enum": [
              "auto",
              "enabled",
              "disabled"
            ],
            "default": "auto"
          },
          "max_sites_per_query": {
            "title": "Maximum sites per metrics query",
            "description": "Maximum site IDs sent in one accountMetrics query.",
            "type": "integer",
            "minimum": 1,
            "maximum": 1000,
            "default": 50
          }
        }
      },
      "events": {
        "title": "Events",
        "type": "object",
        "properties": {
          "enabled": {
            "title": "Collect events",
            "description": "Controls marker-based eventsFeed collection.",
            "type": "string",
            "enum": [
              "auto",
              "enabled",
              "disabled"
            ],
            "default": "auto"
          },
          "marker_file": {
            "title": "Events marker file",
            "description": "Optional explicit file path used to persist the eventsFeed marker. Set this when multiple jobs intentionally monitor the same account, endpoint, and vnode independently.",
            "type": "string"
          },
          "max_pages_per_cycle": {
            "title": "Maximum EventsFeed pages per cycle",
            "description": "Maximum marker pages drained from eventsFeed during one collection cycle.",
            "type": "integer",
            "minimum": 1,
            "maximum": 100,
            "default": 10
          },
          "max_cardinality": {
            "title": "Maximum event series",
            "description": "Maximum unique event type/subtype/severity/status series before excess events are collapsed into an other bucket.",
            "type": "integer",
            "minimum": 1,
            "maximum": 10000,
            "default": 50
          }
        }
      },
      "bgp": {
        "title": "BGP",
        "type": "object",
        "properties": {
          "enabled": {
            "title": "Collect BGP status",
            "description": "Controls siteBgpStatus collection.",
            "type": "string",
            "enum": [
              "auto",
              "enabled",
              "disabled"
            ],
            "default": "auto"
          },
          "refresh_every": {
            "title": "BGP refresh interval",
            "description": "Minimum interval between BGP status refreshes, in seconds.",
            "type": "integer",
            "minimum": 60,
            "default": 300
          },
          "max_sites_per_collection": {
            "title": "Maximum sites per BGP collection",
            "description": "Maximum sites queried for BGP status during one refresh.",
            "type": "integer",
            "minimum": 1,
            "maximum": 1000,
            "default": 25
          },
          "peer_selector": {
            "title": "BGP peer selector",
            "description": "Space-separated simple patterns matched against BGP peer remote IP or remote ASN. Use exclusions such as '!64512 *'. Exclusions win across BGP peer identity fields.",
            "type": "string",
            "default": "*"
          },
          "max_peers_per_site": {
            "title": "Maximum BGP peers per site",
            "description": "Maximum BGP peers collected per selected site after bgp.peer_selector filtering. Set to 0 to disable this cap.",
            "type": "integer",
            "minimum": 0,
            "maximum": 10000,
            "default": 32
          }
        }
      },
      "topology": {
        "title": "Topology",
        "type": "object",
        "properties": {
          "enabled": {
            "title": "Build topology",
            "description": "Controls topology function data generation.",
            "type": "string",
            "enum": [
              "auto",
              "enabled",
              "disabled"
            ],
            "default": "auto"
          }
        }
      },
      "retry": {
        "title": "Retry",
        "type": "object",
        "properties": {
          "attempts": {
            "title": "Attempts",
            "description": "Maximum attempts for retryable Cato API errors.",
            "type": "integer",
            "minimum": 1,
            "maximum": 10,
            "default": 5
          },
          "wait_min": {
            "title": "Minimum wait",
            "description": "Initial retry wait.",
            "type": "number",
            "minimum": 0,
            "default": 5
          },
          "wait_max": {
            "title": "Maximum wait",
            "description": "Maximum retry wait.",
            "type": "number",
            "minimum": 0,
            "default": 30
          }
        }
      },
      "vnode": {
        "title": "Vnode",
        "description": "Associates this data collection job with a Virtual Node.",
        "type": "string"
      }
    },
    "required": [
      "account_id",
      "api_key"
    ]
  },
  "uiSchema": {
    "uiOptions": {
      "fullPage": true
    },
    "api_key": {
      "ui:widget": "password"
    },
    "vnode": {
      "ui:placeholder": "To use this option, first create a Virtual Node and then reference its name here."
    }
  }
}
